alexasomba_paystack/__init__.py
alexasomba_paystack/api_client.py
alexasomba_paystack/api_response.py
alexasomba_paystack/configuration.py
alexasomba_paystack/exceptions.py
alexasomba_paystack/extras.py
alexasomba_paystack/py.typed
alexasomba_paystack/rest.py
alexasomba_paystack/api/__init__.py
alexasomba_paystack/api/apple_pay_api.py
alexasomba_paystack/api/balance_api.py
alexasomba_paystack/api/bank_api.py
alexasomba_paystack/api/bulk_charge_api.py
alexasomba_paystack/api/charge_api.py
alexasomba_paystack/api/customer_api.py
alexasomba_paystack/api/dedicated_virtual_account_api.py
alexasomba_paystack/api/direct_debit_api.py
alexasomba_paystack/api/dispute_api.py
alexasomba_paystack/api/integration_api.py
alexasomba_paystack/api/miscellaneous_api.py
alexasomba_paystack/api/order_api.py
alexasomba_paystack/api/page_api.py
alexasomba_paystack/api/payment_request_api.py
alexasomba_paystack/api/plan_api.py
alexasomba_paystack/api/product_api.py
alexasomba_paystack/api/refund_api.py
alexasomba_paystack/api/settlement_api.py
alexasomba_paystack/api/split_api.py
alexasomba_paystack/api/storefront_api.py
alexasomba_paystack/api/subaccount_api.py
alexasomba_paystack/api/subscription_api.py
alexasomba_paystack/api/terminal_api.py
alexasomba_paystack/api/transaction_api.py
alexasomba_paystack/api/transfer_api.py
alexasomba_paystack/api/transfer_recipient_api.py
alexasomba_paystack/api/verification_api.py
alexasomba_paystack/api/virtual_terminal_api.py
alexasomba_paystack/models/__init__.py
alexasomba_paystack/models/accepted.py
alexasomba_paystack/models/apple_pay_create_ok_model.py
alexasomba_paystack/models/apple_pay_param.py
alexasomba_paystack/models/balance_check_response.py
alexasomba_paystack/models/balance_check_response_array.py
alexasomba_paystack/models/balance_fetch_ledger_response.py
alexasomba_paystack/models/balance_fetch_ledger_response_array.py
alexasomba_paystack/models/bank.py
alexasomba_paystack/models/bank_validate_request.py
alexasomba_paystack-1.1.6.dist-info/METADATA
alexasomba_paystack-1.1.6.dist-info/WHEEL
alexasomba_paystack-1.1.6.dist-info/top_level.txt
alexasomba_paystack-1.1.6.dist-info/RECORD
