Metadata-Version: 2.4
Name: alexasomba-paystack
Version: 1.1.6
Summary: Paystack
Home-page: 
Author: OpenAPI Generator community
Author-email: techsupport@paystack.com
Keywords: OpenAPI,OpenAPI-Generator,Paystack
Requires-Dist: urllib3<2.1.0,>=1.25.3
Requires-Dist: python-dateutil
Requires-Dist: pydantic<2,>=1.10.5
Requires-Dist: aenum
Dynamic: author
Dynamic: author-email
Dynamic: description
Dynamic: description-content-type
Dynamic: keywords
Dynamic: requires-dist
Dynamic: summary
